README.md
setup.py
lib/playbook_checker/__init__.py
lib/playbook_checker/__main__.py
lib/playbook_checker/checker.py
lib/playbook_checker/utils.py
lib/playbook_checker.egg-info/PKG-INFO
lib/playbook_checker.egg-info/SOURCES.txt
lib/playbook_checker.egg-info/dependency_links.txt
lib/playbook_checker.egg-info/entry_points.txt
lib/playbook_checker.egg-info/top_level.txt