Metadata-Version: 2.1
Name: playbook-checker
Version: 0.1.2
Summary: TODO
Home-page: https://github.com/vengaar/playbook-checker
Author: Olivier Perriot
Author-email: 
License: GPLv3
Platform: UNKNOWN
Classifier: Programming Language :: Python :: 3
Classifier: License :: OSI Approved :: GNU General Public License v3 or later (GPLv3+)
Classifier: Operating System :: OS Independent
Requires-Python: >=3.6
